wheke_auth/__about__.py
wheke_auth/__init__.py
wheke_auth/cli.py
wheke_auth/exceptions.py
wheke_auth/models.py
wheke_auth/py.typed
wheke_auth/repository.py
wheke_auth/routes.py
wheke_auth/security.py
wheke_auth/service.py
wheke_auth/settings.py
wheke_auth-0.0.1a3.dist-info/METADATA
wheke_auth-0.0.1a3.dist-info/WHEEL
wheke_auth-0.0.1a3.dist-info/licenses/LICENSE.txt
wheke_auth-0.0.1a3.dist-info/RECORD
